{
  "galaxy_stats": {
    "missionsWon": 260246086,
    "missionsLost": 27321465,
    "missionTime": 632113864152,
    "bugKills": 47238088656,
    "automatonKills": 18291639195,
    "illuminateKills": 28,
    "bulletsFired": 358369101221,
    "bulletsHit": 401118899971,
    "timePlayed": 632113864152,
    "deaths": 1655164577,
    "revives": 2,
    "friendlies": 225975487,
    "missionSuccessRate": 90,
    "accurracy": 100
  },
  "planets_stats": [
    {
      "planetIndex": 0,
      "missionsWon": 35842,
      "missionsLost": 4335,
      "missionTime": 22915,
      "bugKills": 721,
      "automatonKills": 890,
      "illuminateKills": 16,
      "bulletsFired": 8296,
      "bulletsHit": 9018,
      "timePlayed": 22915,
      "deaths": 85,
      "revives": 0,
      "friendlies": 9,
      "missionSuccessRate": 89,
      "accurracy": 100
    },
    {
      "planetIndex": 2,
      "missionsWon": 1,
      "missionsLost": 0,
      "missionTime": 251,
      "bugKills": 5,
      "automatonKills": 0,
      "illuminateKills": 0,
      "bulletsFired": 20,
      "bulletsHit": 0,
      "timePlayed": 251,
      "deaths": 1,
      "revives": 0,
      "friendlies": 0,
      "missionSuccessRate": 100,
      "accurracy": 0
    },
    {
      "planetIndex": 34,
      "missionsWon": 19926234,
      "missionsLost": 2393296,
      "missionTime": 43327262208,
      "bugKills": 4902349136,
      "automatonKills": 500,
      "illuminateKills": 0,
      "bulletsFired": 26640863301,
      "bulletsHit": 31914084904,
      "timePlayed": 43327262208,
      "deaths": 124047527,
      "revives": 0,
      "friendlies": 17472941,
      "missionSuccessRate": 89,
      "accurracy": 100
    },
    {
      "planetIndex": 64,
      "missionsWon": 5424862,
      "missionsLost": 711926,
      "missionTime": 11559451471,
      "bugKills": 1657549322,
      "automatonKills": 16743,
      "illuminateKills": 0,
      "bulletsFired": 8669223006,
      "bulletsHit": 10322487303,
      "timePlayed": 11559451471,
      "deaths": 41440656,
      "revives": 0,
      "friendlies": 6672853,
      "missionSuccessRate": 88,
      "accurracy": 100
    },
    {
      "planetIndex": 75,
      "missionsWon": 56929,
      "missionsLost": 7176,
      "missionTime": 236476410,
      "bugKills": 34419854,
      "automatonKills": 0,
      "illuminateKills": 0,
      "bulletsFired": 148543364,
      "bulletsHit": 182618786,
      "timePlayed": 236476410,
      "deaths": 500627,
      "revives": 0,
      "friendlies": 111473,
      "missionSuccessRate": 88,
      "accurracy": 100
    },
    {
      "planetIndex": 77,
      "missionsWon": 420546,
      "missionsLost": 39798,
      "missionTime": 1541476809,
      "bugKills": 197385048,
      "automatonKills": 0,
      "illuminateKills": 0,
      "bulletsFired": 839939804,
      "bulletsHit": 1027886410,
      "timePlayed": 1541476809,
      "deaths": 3477717,
      "revives": 0,
      "friendlies": 604073,
      "missionSuccessRate": 91,
      "accurracy": 100
    },
    {
      "planetIndex": 78,
      "missionsWon": 17692274,
      "missionsLost": 1530129,
      "missionTime": 37507546196,
      "bugKills": 4822784159,
      "automatonKills": 916,
      "illuminateKills": 0,
      "bulletsFired": 25491631277,
      "bulletsHit": 30733281070,
      "timePlayed": 37507546196,
      "deaths": 89024298,
      "revives": 0,
      "friendlies": 14981277,
      "missionSuccessRate": 92,
      "accurracy": 100
    },
    {
      "planetIndex": 79,
      "missionsWon": 3866073,
      "missionsLost": 411707,
      "missionTime": 10177543938,
      "bugKills": 1353902725,
      "automatonKills": 23,
      "illuminateKills": 0,
      "bulletsFired": 6111997560,
      "bulletsHit": 7414428538,
      "timePlayed": 10177543938,
      "deaths": 22472217,
      "revives": 2,
      "friendlies": 4124614,
      "missionSuccessRate": 90,
      "accurracy": 100
    },
    {
      "planetIndex": 80,
      "missionsWon": 2209353,
      "missionsLost": 169062,
      "missionTime": 7199894109,
      "bugKills": 909983054,
      "automatonKills": 61,
      "illuminateKills": 0,
      "bulletsFired": 4245849499,
      "bulletsHit": 5225974341,
      "timePlayed": 7199894109,
      "deaths": 17170640,
      "revives": 0,
      "friendlies": 2635801,
      "missionSuccessRate": 92,
      "accurracy": 100
    },
    {
      "planetIndex": 85,
      "missionsWon": 0,
      "missionsLost": 0,
      "missionTime": 15,
      "bugKills": 0,
      "automatonKills": 0,
      "illuminateKills": 0,
      "bulletsFired": 0,
      "bulletsHit": 0,
      "timePlayed": 15,
      "deaths": 0,
      "revives": 0,
      "friendlies": 0,
      "missionSuccessRate": 0,
      "accurracy": 0
    },
    {
      "planetIndex": 107,
      "missionsWon": 8977,
      "missionsLost": 1230,
      "missionTime": 9016555,
      "bugKills": 0,
      "automatonKills": 610618,
      "illuminateKills": 0,
      "bulletsFired": 4148535,
      "bulletsHit": 2635342,
      "timePlayed": 9016555,
      "deaths": 31008,
      "revives": 0,
      "friendlies": 2971,
      "missionSuccessRate": 87,
      "accurracy": 63
    },
    {
      "planetIndex": 112,
      "missionsWon": 7694206,
      "missionsLost": 1221144,
      "missionTime": 30491742328,
      "bugKills": 589,
      "automatonKills": 2302915890,
      "illuminateKills": 0,
      "bulletsFired": 14190091004,
      "bulletsHit": 14833406640,
      "timePlayed": 30491742328,
      "deaths": 73418686,
      "revives": 0,
      "friendlies": 8118356,
      "missionSuccessRate": 86,
      "accurracy": 100
    },
    {
      "planetIndex": 113,
      "missionsWon": 1687588,
      "missionsLost": 184331,
      "missionTime": 6239133625,
      "bugKills": 503,
      "automatonKills": 451568904,
      "illuminateKills": 0,
      "bulletsFired": 2549163934,
      "bulletsHit": 2651054864,
      "timePlayed": 6239133625,
      "deaths": 14506949,
      "revives": 0,
      "friendlies": 1747239,
      "missionSuccessRate": 90,
      "accurracy": 100
    },
    {
      "planetIndex": 115,
      "missionsWon": 2575880,
      "missionsLost": 232190,
      "missionTime": 9184262330,
      "bugKills": 101,
      "automatonKills": 594520135,
      "illuminateKills": 0,
      "bulletsFired": 3635309297,
      "bulletsHit": 3684392162,
      "timePlayed": 9184262330,
      "deaths": 25222528,
      "revives": 0,
      "friendlies": 3085477,
      "missionSuccessRate": 91,
      "accurracy": 100
    },
    {
      "planetIndex": 125,
      "missionsWon": 10562659,
      "missionsLost": 717607,
      "missionTime": 20644572887,
      "bugKills": 2678904654,
      "automatonKills": 93142,
      "illuminateKills": 0,
      "bulletsFired": 13249407270,
      "bulletsHit": 13157162523,
      "timePlayed": 20644572887,
      "deaths": 48295931,
      "revives": 0,
      "friendlies": 7959586,
      "missionSuccessRate": 93,
      "accurracy": 99
    },
    {
      "planetIndex": 126,
      "missionsWon": 16777468,
      "missionsLost": 1092684,
      "missionTime": 28943732103,
      "bugKills": 3620473821,
      "automatonKills": 52464,
      "illuminateKills": 0,
      "bulletsFired": 18592802311,
      "bulletsHit": 18583068500,
      "timePlayed": 28943732103,
      "deaths": 75623880,
      "revives": 0,
      "friendlies": 12153941,
      "missionSuccessRate": 93,
      "accurracy": 99
    },
    {
      "planetIndex": 127,
      "missionsWon": 3789808,
      "missionsLost": 352493,
      "missionTime": 12282843082,
      "bugKills": 1666125660,
      "automatonKills": 145,
      "illuminateKills": 0,
      "bulletsFired": 7597543636,
      "bulletsHit": 9228354790,
      "timePlayed": 12282843082,
      "deaths": 26185706,
      "revives": 0,
      "friendlies": 4586123,
      "missionSuccessRate": 91,
      "accurracy": 100
    },
    {
      "planetIndex": 129,
      "missionsWon": 3119886,
      "missionsLost": 221210,
      "missionTime": 10469434913,
      "bugKills": 1384486963,
      "automatonKills": 72,
      "illuminateKills": 0,
      "bulletsFired": 6043509849,
      "bulletsHit": 7439165246,
      "timePlayed": 10469434913,
      "deaths": 23061157,
      "revives": 0,
      "friendlies": 3976498,
      "missionSuccessRate": 93,
      "accurracy": 100
    },
    {
      "planetIndex": 152,
      "missionsWon": 5114320,
      "missionsLost": 484857,
      "missionTime": 15339431901,
      "bugKills": 24794,
      "automatonKills": 1005777120,
      "illuminateKills": 0,
      "bulletsFired": 7276163889,
      "bulletsHit": 6963315453,
      "timePlayed": 15339431901,
      "deaths": 39436780,
      "revives": 0,
      "friendlies": 3648054,
      "missionSuccessRate": 91,
      "accurracy": 95
    },
    {
      "planetIndex": 153,
      "missionsWon": 5295514,
      "missionsLost": 659823,
      "missionTime": 4418287608,
      "bugKills": 519,
      "automatonKills": 344374842,
      "illuminateKills": 0,
      "bulletsFired": 2494312574,
      "bulletsHit": 2454520332,
      "timePlayed": 4418287608,
      "deaths": 21556383,
      "revives": 0,
      "friendlies": 2108247,
      "missionSuccessRate": 88,
      "accurracy": 98
    },
    {
      "planetIndex": 154,
      "missionsWon": 1588387,
      "missionsLost": 68648,
      "missionTime": 1666502547,
      "bugKills": 1184,
      "automatonKills": 123784538,
      "illuminateKills": 0,
      "bulletsFired": 690796508,
      "bulletsHit": 564589321,
      "timePlayed": 1666502547,
      "deaths": 4261748,
      "revives": 0,
      "friendlies": 632634,
      "missionSuccessRate": 95,
      "accurracy": 81
    },
    {
      "planetIndex": 155,
      "missionsWon": 5083,
      "missionsLost": 1575,
      "missionTime": 4607984,
      "bugKills": 0,
      "automatonKills": 386330,
      "illuminateKills": 0,
      "bulletsFired": 2740050,
      "bulletsHit": 2222051,
      "timePlayed": 4607984,
      "deaths": 21236,
      "revives": 0,
      "friendlies": 1827,
      "missionSuccessRate": 76,
      "accurracy": 81
    },
    {
      "planetIndex": 156,
      "missionsWon": 579442,
      "missionsLost": 84643,
      "missionTime": 1748260050,
      "bugKills": 0,
      "automatonKills": 117339063,
      "illuminateKills": 0,
      "bulletsFired": 759266662,
      "bulletsHit": 756789206,
      "timePlayed": 1748260050,
      "deaths": 5152897,
      "revives": 0,
      "friendlies": 496425,
      "missionSuccessRate": 87,
      "accurracy": 99
    },
    {
      "planetIndex": 157,
      "missionsWon": 285997,
      "missionsLost": 57152,
      "missionTime": 1092251590,
      "bugKills": 0,
      "automatonKills": 77141616,
      "illuminateKills": 0,
      "bulletsFired": 498085508,
      "bulletsHit": 506259170,
      "timePlayed": 1092251590,
      "deaths": 2874769,
      "revives": 0,
      "friendlies": 292593,
      "missionSuccessRate": 83,
      "accurracy": 100
    },
    {
      "planetIndex": 158,
      "missionsWon": 1706787,
      "missionsLost": 167147,
      "missionTime": 5855280128,
      "bugKills": 0,
      "automatonKills": 420666290,
      "illuminateKills": 0,
      "bulletsFired": 2553906130,
      "bulletsHit": 2593668310,
      "timePlayed": 5855280128,
      "deaths": 13882622,
      "revives": 0,
      "friendlies": 1347182,
      "missionSuccessRate": 91,
      "accurracy": 100
    },
    {
      "planetIndex": 159,
      "missionsWon": 356858,
      "missionsLost": 48034,
      "missionTime": 1182798614,
      "bugKills": 0,
      "automatonKills": 75697898,
      "illuminateKills": 0,
      "bulletsFired": 512987383,
      "bulletsHit": 507140680,
      "timePlayed": 1182798614,
      "deaths": 3363721,
      "revives": 0,
      "friendlies": 322921,
      "missionSuccessRate": 88,
      "accurracy": 98
    },
    {
      "planetIndex": 160,
      "missionsWon": 1583460,
      "missionsLost": 247985,
      "missionTime": 5845818598,
      "bugKills": 119,
      "automatonKills": 391737183,
      "illuminateKills": 0,
      "bulletsFired": 2542683257,
      "bulletsHit": 2595826894,
      "timePlayed": 5845818598,
      "deaths": 16978877,
      "revives": 0,
      "friendlies": 1668728,
      "missionSuccessRate": 86,
      "accurracy": 100
    },
    {
      "planetIndex": 168,
      "missionsWon": 10635765,
      "missionsLost": 999584,
      "missionTime": 22905151952,
      "bugKills": 2991240051,
      "automatonKills": 0,
      "illuminateKills": 0,
      "bulletsFired": 14566874471,
      "bulletsHit": 17694341749,
      "timePlayed": 22905151952,
      "deaths": 67822581,
      "revives": 0,
      "friendlies": 10340191,
      "missionSuccessRate": 91,
      "accurracy": 100
    },
    {
      "planetIndex": 169,
      "missionsWon": 23334310,
      "missionsLost": 2602554,
      "missionTime": 53851905512,
      "bugKills": 7148527359,
      "automatonKills": 750,
      "illuminateKills": 0,
      "bulletsFired": 36075933653,
      "bulletsHit": 43254624566,
      "timePlayed": 53851905512,
      "deaths": 128091711,
      "revives": 0,
      "friendlies": 23359235,
      "missionSuccessRate": 89,
      "accurracy": 100
    },
    {
      "planetIndex": 170,
      "missionsWon": 15803461,
      "missionsLost": 1678593,
      "missionTime": 38246332305,
      "bugKills": 4839061698,
      "automatonKills": 214,
      "illuminateKills": 0,
      "bulletsFired": 25724353376,
      "bulletsHit": 30719860872,
      "timePlayed": 38246332305,
      "deaths": 91932750,
      "revives": 0,
      "friendlies": 15941486,
      "missionSuccessRate": 90,
      "accurracy": 100
    },
    {
      "planetIndex": 172,
      "missionsWon": 0,
      "missionsLost": 0,
      "missionTime": 844,
      "bugKills": 49,
      "automatonKills": 0,
      "illuminateKills": 0,
      "bulletsFired": 496,
      "bulletsHit": 644,
      "timePlayed": 844,
      "deaths": 13,
      "revives": 0,
      "friendlies": 0,
      "missionSuccessRate": 0,
      "accurracy": 100
    },
    {
      "planetIndex": 194,
      "missionsWon": 7593839,
      "missionsLost": 798534,
      "missionTime": 29159356399,
      "bugKills": 188,
      "automatonKills": 2085863452,
      "illuminateKills": 0,
      "bulletsFired": 12804228227,
      "bulletsHit": 13313082062,
      "timePlayed": 29159356399,
      "deaths": 68207221,
      "revives": 0,
      "friendlies": 6695465,
      "missionSuccessRate": 90,
      "accurracy": 100
    },
    {
      "planetIndex": 195,
      "missionsWon": 3311349,
      "missionsLost": 270871,
      "missionTime": 12234663270,
      "bugKills": 2,
      "automatonKills": 839075126,
      "illuminateKills": 0,
      "bulletsFired": 6204332101,
      "bulletsHit": 6363386556,
      "timePlayed": 12234663270,
      "deaths": 29893432,
      "revives": 0,
      "friendlies": 2619779,
      "missionSuccessRate": 92,
      "accurracy": 100
    },
    {
      "planetIndex": 196,
      "missionsWon": 5120593,
      "missionsLost": 714275,
      "missionTime": 5330169875,
      "bugKills": 597,
      "automatonKills": 376400041,
      "illuminateKills": 0,
      "bulletsFired": 2770384496,
      "bulletsHit": 2757979074,
      "timePlayed": 5330169875,
      "deaths": 25036520,
      "revives": 0,
      "friendlies": 2364775,
      "missionSuccessRate": 87,
      "accurracy": 99
    },
    {
      "planetIndex": 197,
      "missionsWon": 3864079,
      "missionsLost": 388038,
      "missionTime": 2983914302,
      "bugKills": 24729,
      "automatonKills": 231317626,
      "illuminateKills": 0,
      "bulletsFired": 1614722056,
      "bulletsHit": 1216961752,
      "timePlayed": 2983914302,
      "deaths": 12079735,
      "revives": 0,
      "friendlies": 1473488,
      "missionSuccessRate": 90,
      "accurracy": 75
    },
    {
      "planetIndex": 198,
      "missionsWon": 6154563,
      "missionsLost": 561241,
      "missionTime": 22694486736,
      "bugKills": 569,
      "automatonKills": 1568012234,
      "illuminateKills": 0,
      "bulletsFired": 9473889356,
      "bulletsHit": 9937805022,
      "timePlayed": 22694486736,
      "deaths": 53503865,
      "revives": 0,
      "friendlies": 5485059,
      "missionSuccessRate": 91,
      "accurracy": 100
    },
    {
      "planetIndex": 199,
      "missionsWon": 3202383,
      "missionsLost": 372776,
      "missionTime": 12041851371,
      "bugKills": 444,
      "automatonKills": 829008047,
      "illuminateKills": 0,
      "bulletsFired": 5364705090,
      "bulletsHit": 5425260688,
      "timePlayed": 12041851371,
      "deaths": 32392179,
      "revives": 0,
      "friendlies": 2856801,
      "missionSuccessRate": 89,
      "accurracy": 100
    },
    {
      "planetIndex": 200,
      "missionsWon": 1060882,
      "missionsLost": 169318,
      "missionTime": 3917970254,
      "bugKills": 43,
      "automatonKills": 277540199,
      "illuminateKills": 0,
      "bulletsFired": 1811228036,
      "bulletsHit": 1864040302,
      "timePlayed": 3917970254,
      "deaths": 10485562,
      "revives": 0,
      "friendlies": 1092954,
      "missionSuccessRate": 86,
      "accurracy": 100
    },
    {
      "planetIndex": 201,
      "missionsWon": 1116828,
      "missionsLost": 163398,
      "missionTime": 3972740046,
      "bugKills": 123,
      "automatonKills": 263872230,
      "illuminateKills": 0,
      "bulletsFired": 1728018902,
      "bulletsHit": 1743553068,
      "timePlayed": 3972740046,
      "deaths": 11455535,
      "revives": 0,
      "friendlies": 1162005,
      "missionSuccessRate": 87,
      "accurracy": 100
    },
    {
      "planetIndex": 202,
      "missionsWon": 50,
      "missionsLost": 6,
      "missionTime": 143975,
      "bugKills": 0,
      "automatonKills": 10482,
      "illuminateKills": 0,
      "bulletsFired": 76320,
      "bulletsHit": 80386,
      "timePlayed": 143975,
      "deaths": 396,
      "revives": 0,
      "friendlies": 20,
      "missionSuccessRate": 89,
      "accurracy": 100
    },
    {
      "planetIndex": 203,
      "missionsWon": 8935538,
      "missionsLost": 1331320,
      "missionTime": 30865002745,
      "bugKills": 1315,
      "automatonKills": 2057868478,
      "illuminateKills": 0,
      "bulletsFired": 13600118401,
      "bulletsHit": 13922235894,
      "timePlayed": 30865002745,
      "deaths": 88083430,
      "revives": 0,
      "friendlies": 7917266,
      "missionSuccessRate": 87,
      "accurracy": 100
    },
    {
      "planetIndex": 204,
      "missionsWon": 117396,
      "missionsLost": 12227,
      "missionTime": 321779409,
      "bugKills": 45,
      "automatonKills": 21186986,
      "illuminateKills": 0,
      "bulletsFired": 135692509,
      "bulletsHit": 135790320,
      "timePlayed": 321779409,
      "deaths": 928605,
      "revives": 0,
      "friendlies": 87246,
      "missionSuccessRate": 90,
      "accurracy": 100
    },
    {
      "planetIndex": 211,
      "missionsWon": 3543236,
      "missionsLost": 349044,
      "missionTime": 5726293735,
      "bugKills": 662564859,
      "automatonKills": 485,
      "illuminateKills": 0,
      "bulletsFired": 3676624261,
      "bulletsHit": 4385499302,
      "timePlayed": 5726293735,
      "deaths": 16867439,
      "revives": 0,
      "friendlies": 2627904,
      "missionSuccessRate": 91,
      "accurracy": 100
    },
    {
      "planetIndex": 212,
      "missionsWon": 15101365,
      "missionsLost": 1735697,
      "missionTime": 32687440295,
      "bugKills": 4211239216,
      "automatonKills": 307,
      "illuminateKills": 0,
      "bulletsFired": 21725407364,
      "bulletsHit": 25976280090,
      "timePlayed": 32687440295,
      "deaths": 84999413,
      "revives": 0,
      "friendlies": 14488269,
      "missionSuccessRate": 89,
      "accurracy": 100
    },
    {
      "planetIndex": 214,
      "missionsWon": 3448152,
      "missionsLost": 219743,
      "missionTime": 11572466768,
      "bugKills": 1438314929,
      "automatonKills": 87,
      "illuminateKills": 0,
      "bulletsFired": 6505059333,
      "bulletsHit": 7954882832,
      "timePlayed": 11572466768,
      "deaths": 26636105,
      "revives": 0,
      "friendlies": 4419332,
      "missionSuccessRate": 94,
      "accurracy": 100
    },
    {
      "planetIndex": 217,
      "missionsWon": 2699597,
      "missionsLost": 237603,
      "missionTime": 9725861347,
      "bugKills": 1214914320,
      "automatonKills": 0,
      "illuminateKills": 0,
      "bulletsFired": 5475578817,
      "bulletsHit": 6736865904,
      "timePlayed": 9725861347,
      "deaths": 22246261,
      "revives": 0,
      "friendlies": 3644216,
      "missionSuccessRate": 91,
      "accurracy": 100
    },
    {
      "planetIndex": 238,
      "missionsWon": 5661579,
      "missionsLost": 482143,
      "missionTime": 16198865954,
      "bugKills": 20049,
      "automatonKills": 1034177528,
      "illuminateKills": 0,
      "bulletsFired": 7920460874,
      "bulletsHit": 7584533912,
      "timePlayed": 16198865954,
      "deaths": 43814247,
      "revives": 0,
      "friendlies": 3998773,
      "missionSuccessRate": 92,
      "accurracy": 95
    },
    {
      "planetIndex": 239,
      "missionsWon": 4910,
      "missionsLost": 1881,
      "missionTime": 4694427,
      "bugKills": 0,
      "automatonKills": 335789,
      "illuminateKills": 0,
      "bulletsFired": 2621541,
      "bulletsHit": 2577752,
      "timePlayed": 4694427,
      "deaths": 24209,
      "revives": 0,
      "friendlies": 1179,
      "missionSuccessRate": 72,
      "accurracy": 98
    },
    {
      "planetIndex": 240,
      "missionsWon": 5329240,
      "missionsLost": 663628,
      "missionTime": 3880230156,
      "bugKills": 5338,
      "automatonKills": 307795526,
      "illuminateKills": 0,
      "bulletsFired": 2080579781,
      "bulletsHit": 1596900925,
      "timePlayed": 3880230156,
      "deaths": 16038793,
      "revives": 0,
      "friendlies": 1925911,
      "missionSuccessRate": 88,
      "accurracy": 76
    },
    {
      "planetIndex": 241,
      "missionsWon": 7536782,
      "missionsLost": 985851,
      "missionTime": 8431990433,
      "bugKills": 37206,
      "automatonKills": 664999175,
      "illuminateKills": 0,
      "bulletsFired": 4653559342,
      "bulletsHit": 4321458569,
      "timePlayed": 8431990433,
      "deaths": 31832811,
      "revives": 0,
      "friendlies": 3164497,
      "missionSuccessRate": 88,
      "accurracy": 92
    },
    {
      "planetIndex": 242,
      "missionsWon": 3381558,
      "missionsLost": 481652,
      "missionTime": 3646643080,
      "bugKills": 1510,
      "automatonKills": 269129223,
      "illuminateKills": 0,
      "bulletsFired": 1870255412,
      "bulletsHit": 1862281804,
      "timePlayed": 3646643080,
      "deaths": 16419927,
      "revives": 0,
      "friendlies": 1562469,
      "missionSuccessRate": 87,
      "accurracy": 99
    },
    {
      "planetIndex": 243,
      "missionsWon": 2774950,
      "missionsLost": 306241,
      "missionTime": 4714815349,
      "bugKills": 245,
      "automatonKills": 341043312,
      "illuminateKills": 0,
      "bulletsFired": 2664164840,
      "bulletsHit": 2790159488,
      "timePlayed": 4714815349,
      "deaths": 15200201,
      "revives": 0,
      "friendlies": 1469071,
      "missionSuccessRate": 90,
      "accurracy": 100
    },
    {
      "planetIndex": 244,
      "missionsWon": 2284444,
      "missionsLost": 221315,
      "missionTime": 10001289059,
      "bugKills": 56,
      "automatonKills": 641689472,
      "illuminateKills": 0,
      "bulletsFired": 3901200209,
      "bulletsHit": 4002962864,
      "timePlayed": 10001289059,
      "deaths": 22454105,
      "revives": 0,
      "friendlies": 2136064,
      "missionSuccessRate": 91,
      "accurracy": 100
    },
    {
      "planetIndex": 245,
      "missionsWon": 689713,
      "missionsLost": 76077,
      "missionTime": 2577065582,
      "bugKills": 0,
      "automatonKills": 180890337,
      "illuminateKills": 0,
      "bulletsFired": 1046890850,
      "bulletsHit": 1076806640,
      "timePlayed": 2577065582,
      "deaths": 6853005,
      "revives": 0,
      "friendlies": 668087,
      "missionSuccessRate": 90,
      "accurracy": 100
    },
    {
      "planetIndex": 246,
      "missionsWon": 709902,
      "missionsLost": 48917,
      "missionTime": 2761536919,
      "bugKills": 132,
      "automatonKills": 194415632,
      "illuminateKills": 0,
      "bulletsFired": 1088062228,
      "bulletsHit": 1144720416,
      "timePlayed": 2761536919,
      "deaths": 6135368,
      "revives": 0,
      "friendlies": 653550,
      "missionSuccessRate": 93,
      "accurracy": 100
    },
    {
      "planetIndex": 247,
      "missionsWon": 770752,
      "missionsLost": 69131,
      "missionTime": 2960244948,
      "bugKills": 0,
      "automatonKills": 200310284,
      "illuminateKills": 0,
      "bulletsFired": 1299109050,
      "bulletsHit": 1323111918,
      "timePlayed": 2960244948,
      "deaths": 7683531,
      "revives": 0,
      "friendlies": 647728,
      "missionSuccessRate": 91,
      "accurracy": 100
    },
    {
      "planetIndex": 248,
      "missionsWon": 54,
      "missionsLost": 8,
      "missionTime": 169996,
      "bugKills": 0,
      "automatonKills": 10782,
      "illuminateKills": 0,
      "bulletsFired": 81925,
      "bulletsHit": 82338,
      "timePlayed": 169996,
      "deaths": 534,
      "revives": 0,
      "friendlies": 46,
      "missionSuccessRate": 87,
      "accurracy": 100
    },
    {
      "planetIndex": 259,
      "missionsWon": 3691348,
      "missionsLost": 269617,
      "missionTime": 11731134899,
      "bugKills": 1503740653,
      "automatonKills": 0,
      "illuminateKills": 0,
      "bulletsFired": 7243913472,
      "bulletsHit": 8666430146,
      "timePlayed": 11731134899,
      "deaths": 26036443,
      "revives": 0,
      "friendlies": 4420778,
      "missionSuccessRate": 93,
      "accurracy": 100
    },
    {
      "planetIndex": 260,
      "missionsWon": 3033,
      "missionsLost": 0,
      "missionTime": 1045,
      "bugKills": 0,
      "automatonKills": 8,
      "illuminateKills": 12,
      "bulletsFired": 508,
      "bulletsHit": 262,
      "timePlayed": 1045,
      "deaths": 4,
      "revives": 0,
      "friendlies": 0,
      "missionSuccessRate": 100,
      "accurracy": 51
    },
    {
      "planetIndex": 261,
      "missionsWon": 1,
      "missionsLost": 0,
      "missionTime": 0,
      "bugKills": 0,
      "automatonKills": 0,
      "illuminateKills": 0,
      "bulletsFired": 0,
      "bulletsHit": 0,
      "timePlayed": 0,
      "deaths": 0,
      "revives": 0,
      "friendlies": 0,
      "missionSuccessRate": 100,
      "accurracy": 0
    }
  ]
}