{
  "galaxy_stats": {
    "missionsWon": 233725632,
    "missionsLost": 25044881,
    "missionTime": 533768991038,
    "bugKills": 38871554486,
    "automatonKills": 15766640110,
    "illuminateKills": 28,
    "bulletsFired": 306075853449,
    "bulletsHit": 339716320823,
    "timePlayed": 533768991038,
    "deaths": 1424829717,
    "revives": 2,
    "friendlies": 193404245,
    "missionSuccessRate": 90,
    "accurracy": 100
  },
  "planets_stats": [
    {
      "planetIndex": 0,
      "missionsWon": 35842,
      "missionsLost": 4332,
      "missionTime": 22915,
      "bugKills": 721,
      "automatonKills": 890,
      "illuminateKills": 16,
      "bulletsFired": 8296,
      "bulletsHit": 9018,
      "timePlayed": 22915,
      "deaths": 85,
      "revives": 0,
      "friendlies": 9,
      "missionSuccessRate": 89,
      "accurracy": 100
    },
    {
      "planetIndex": 2,
      "missionsWon": 1,
      "missionsLost": 0,
      "missionTime": 251,
      "bugKills": 5,
      "automatonKills": 0,
      "illuminateKills": 0,
      "bulletsFired": 20,
      "bulletsHit": 0,
      "timePlayed": 251,
      "deaths": 1,
      "revives": 0,
      "friendlies": 0,
      "missionSuccessRate": 100,
      "accurracy": 0
    },
    {
      "planetIndex": 34,
      "missionsWon": 18679730,
      "missionsLost": 2270506,
      "missionTime": 39130501733,
      "bugKills": 4407104851,
      "automatonKills": 500,
      "illuminateKills": 0,
      "bulletsFired": 24224096226,
      "bulletsHit": 28990586098,
      "timePlayed": 39130501733,
      "deaths": 113909624,
      "revives": 0,
      "friendlies": 15963538,
      "missionSuccessRate": 89,
      "accurracy": 100
    },
    {
      "planetIndex": 64,
      "missionsWon": 3317105,
      "missionsLost": 381835,
      "missionTime": 4044185242,
      "bugKills": 539897441,
      "automatonKills": 16718,
      "illuminateKills": 0,
      "bulletsFired": 3397226816,
      "bulletsHit": 3743473213,
      "timePlayed": 4044185242,
      "deaths": 14474647,
      "revives": 0,
      "friendlies": 2452170,
      "missionSuccessRate": 89,
      "accurracy": 100
    },
    {
      "planetIndex": 77,
      "missionsWon": 466,
      "missionsLost": 170,
      "missionTime": 526742,
      "bugKills": 61902,
      "automatonKills": 0,
      "illuminateKills": 0,
      "bulletsFired": 390605,
      "bulletsHit": 470160,
      "timePlayed": 526742,
      "deaths": 2250,
      "revives": 0,
      "friendlies": 166,
      "missionSuccessRate": 73,
      "accurracy": 100
    },
    {
      "planetIndex": 78,
      "missionsWon": 14866616,
      "missionsLost": 1375480,
      "missionTime": 27322890907,
      "bugKills": 3409219838,
      "automatonKills": 579,
      "illuminateKills": 0,
      "bulletsFired": 19027038582,
      "bulletsHit": 22766305710,
      "timePlayed": 27322890907,
      "deaths": 68303473,
      "revives": 0,
      "friendlies": 11343270,
      "missionSuccessRate": 91,
      "accurracy": 100
    },
    {
      "planetIndex": 79,
      "missionsWon": 3286864,
      "missionsLost": 335064,
      "missionTime": 7953511087,
      "bugKills": 1052743393,
      "automatonKills": 23,
      "illuminateKills": 0,
      "bulletsFired": 4843743337,
      "bulletsHit": 5887084182,
      "timePlayed": 7953511087,
      "deaths": 18240611,
      "revives": 2,
      "friendlies": 3340747,
      "missionSuccessRate": 90,
      "accurracy": 100
    },
    {
      "planetIndex": 80,
      "missionsWon": 1978129,
      "missionsLost": 131271,
      "missionTime": 6219487056,
      "bugKills": 777519530,
      "automatonKills": 0,
      "illuminateKills": 0,
      "bulletsFired": 3687034191,
      "bulletsHit": 4540135201,
      "timePlayed": 6219487056,
      "deaths": 14956884,
      "revives": 0,
      "friendlies": 2222156,
      "missionSuccessRate": 93,
      "accurracy": 100
    },
    {
      "planetIndex": 107,
      "missionsWon": 8945,
      "missionsLost": 1205,
      "missionTime": 8946245,
      "bugKills": 0,
      "automatonKills": 605841,
      "illuminateKills": 0,
      "bulletsFired": 4102847,
      "bulletsHit": 2595930,
      "timePlayed": 8946245,
      "deaths": 30676,
      "revives": 0,
      "friendlies": 2956,
      "missionSuccessRate": 88,
      "accurracy": 63
    },
    {
      "planetIndex": 112,
      "missionsWon": 5625136,
      "missionsLost": 1054098,
      "missionTime": 22807901226,
      "bugKills": 133,
      "automatonKills": 1723023981,
      "illuminateKills": 0,
      "bulletsFired": 10769378658,
      "bulletsHit": 11328592884,
      "timePlayed": 22807901226,
      "deaths": 55083267,
      "revives": 0,
      "friendlies": 6390152,
      "missionSuccessRate": 84,
      "accurracy": 100
    },
    {
      "planetIndex": 113,
      "missionsWon": 541237,
      "missionsLost": 104275,
      "missionTime": 2174682943,
      "bugKills": 0,
      "automatonKills": 164205206,
      "illuminateKills": 0,
      "bulletsFired": 902311455,
      "bulletsHit": 958480892,
      "timePlayed": 2174682943,
      "deaths": 5094109,
      "revives": 0,
      "friendlies": 702447,
      "missionSuccessRate": 83,
      "accurracy": 100
    },
    {
      "planetIndex": 115,
      "missionsWon": 2574975,
      "missionsLost": 231882,
      "missionTime": 9181597912,
      "bugKills": 101,
      "automatonKills": 594330001,
      "illuminateKills": 0,
      "bulletsFired": 3634071052,
      "bulletsHit": 3683132462,
      "timePlayed": 9181597912,
      "deaths": 25214008,
      "revives": 0,
      "friendlies": 3084913,
      "missionSuccessRate": 91,
      "accurracy": 100
    },
    {
      "planetIndex": 125,
      "missionsWon": 10005257,
      "missionsLost": 656652,
      "missionTime": 18431577603,
      "bugKills": 2375383828,
      "automatonKills": 93142,
      "illuminateKills": 0,
      "bulletsFired": 11971117501,
      "bulletsHit": 11602531165,
      "timePlayed": 18431577603,
      "deaths": 43837387,
      "revives": 0,
      "friendlies": 7150135,
      "missionSuccessRate": 93,
      "accurracy": 96
    },
    {
      "planetIndex": 126,
      "missionsWon": 14893044,
      "missionsLost": 951354,
      "missionTime": 21905702192,
      "bugKills": 2721727069,
      "automatonKills": 52464,
      "illuminateKills": 0,
      "bulletsFired": 14601395258,
      "bulletsHit": 13611657824,
      "timePlayed": 21905702192,
      "deaths": 59180040,
      "revives": 0,
      "friendlies": 9551797,
      "missionSuccessRate": 93,
      "accurracy": 93
    },
    {
      "planetIndex": 127,
      "missionsWon": 3480803,
      "missionsLost": 306312,
      "missionTime": 11083323404,
      "bugKills": 1495158920,
      "automatonKills": 145,
      "illuminateKills": 0,
      "bulletsFired": 6865959603,
      "bulletsHit": 8340756364,
      "timePlayed": 11083323404,
      "deaths": 23695277,
      "revives": 0,
      "friendlies": 4077185,
      "missionSuccessRate": 91,
      "accurracy": 100
    },
    {
      "planetIndex": 129,
      "missionsWon": 1963160,
      "missionsLost": 130843,
      "missionTime": 5997581285,
      "bugKills": 792604575,
      "automatonKills": 72,
      "illuminateKills": 0,
      "bulletsFired": 3484498862,
      "bulletsHit": 4282079460,
      "timePlayed": 5997581285,
      "deaths": 13264792,
      "revives": 0,
      "friendlies": 2247417,
      "missionSuccessRate": 93,
      "accurracy": 100
    },
    {
      "planetIndex": 152,
      "missionsWon": 5114095,
      "missionsLost": 484741,
      "missionTime": 15338765297,
      "bugKills": 24794,
      "automatonKills": 1005731592,
      "illuminateKills": 0,
      "bulletsFired": 7275783553,
      "bulletsHit": 6962946925,
      "timePlayed": 15338765297,
      "deaths": 39434364,
      "revives": 0,
      "friendlies": 3647920,
      "missionSuccessRate": 91,
      "accurracy": 95
    },
    {
      "planetIndex": 153,
      "missionsWon": 5295101,
      "missionsLost": 659608,
      "missionTime": 4417122336,
      "bugKills": 519,
      "automatonKills": 344293757,
      "illuminateKills": 0,
      "bulletsFired": 2493648436,
      "bulletsHit": 2453884530,
      "timePlayed": 4417122336,
      "deaths": 21552090,
      "revives": 0,
      "friendlies": 2107957,
      "missionSuccessRate": 88,
      "accurracy": 98
    },
    {
      "planetIndex": 154,
      "missionsWon": 1588342,
      "missionsLost": 68619,
      "missionTime": 1666354833,
      "bugKills": 1184,
      "automatonKills": 123773429,
      "illuminateKills": 0,
      "bulletsFired": 690714834,
      "bulletsHit": 564506415,
      "timePlayed": 1666354833,
      "deaths": 4261263,
      "revives": 0,
      "friendlies": 632601,
      "missionSuccessRate": 95,
      "accurracy": 81
    },
    {
      "planetIndex": 155,
      "missionsWon": 5038,
      "missionsLost": 1539,
      "missionTime": 4482266,
      "bugKills": 0,
      "automatonKills": 377332,
      "illuminateKills": 0,
      "bulletsFired": 2669718,
      "bulletsHit": 2155291,
      "timePlayed": 4482266,
      "deaths": 20716,
      "revives": 0,
      "friendlies": 1789,
      "missionSuccessRate": 76,
      "accurracy": 80
    },
    {
      "planetIndex": 156,
      "missionsWon": 398958,
      "missionsLost": 56683,
      "missionTime": 1147003776,
      "bugKills": 0,
      "automatonKills": 76801852,
      "illuminateKills": 0,
      "bulletsFired": 497200570,
      "bulletsHit": 498868020,
      "timePlayed": 1147003776,
      "deaths": 3391880,
      "revives": 0,
      "friendlies": 326530,
      "missionSuccessRate": 87,
      "accurracy": 100
    },
    {
      "planetIndex": 157,
      "missionsWon": 285957,
      "missionsLost": 57133,
      "missionTime": 1092148143,
      "bugKills": 0,
      "automatonKills": 77133448,
      "illuminateKills": 0,
      "bulletsFired": 498020990,
      "bulletsHit": 506196596,
      "timePlayed": 1092148143,
      "deaths": 2874388,
      "revives": 0,
      "friendlies": 292579,
      "missionSuccessRate": 83,
      "accurracy": 100
    },
    {
      "planetIndex": 158,
      "missionsWon": 1180421,
      "missionsLost": 117016,
      "missionTime": 4029764447,
      "bugKills": 0,
      "automatonKills": 289056327,
      "illuminateKills": 0,
      "bulletsFired": 1748365784,
      "bulletsHit": 1790182058,
      "timePlayed": 4029764447,
      "deaths": 9552385,
      "revives": 0,
      "friendlies": 925604,
      "missionSuccessRate": 90,
      "accurracy": 100
    },
    {
      "planetIndex": 159,
      "missionsWon": 356792,
      "missionsLost": 47999,
      "missionTime": 1182594308,
      "bugKills": 0,
      "automatonKills": 75683957,
      "illuminateKills": 0,
      "bulletsFired": 512879876,
      "bulletsHit": 507038058,
      "timePlayed": 1182594308,
      "deaths": 3362972,
      "revives": 0,
      "friendlies": 322877,
      "missionSuccessRate": 88,
      "accurracy": 98
    },
    {
      "planetIndex": 160,
      "missionsWon": 1583097,
      "missionsLost": 247738,
      "missionTime": 5844680482,
      "bugKills": 119,
      "automatonKills": 391654292,
      "illuminateKills": 0,
      "bulletsFired": 2542087356,
      "bulletsHit": 2595232130,
      "timePlayed": 5844680482,
      "deaths": 16974224,
      "revives": 0,
      "friendlies": 1668492,
      "missionSuccessRate": 86,
      "accurracy": 100
    },
    {
      "planetIndex": 168,
      "missionsWon": 9311352,
      "missionsLost": 888532,
      "missionTime": 18136891137,
      "bugKills": 2383989003,
      "automatonKills": 0,
      "illuminateKills": 0,
      "bulletsFired": 11860520649,
      "bulletsHit": 14363646105,
      "timePlayed": 18136891137,
      "deaths": 56895438,
      "revives": 0,
      "friendlies": 8582910,
      "missionSuccessRate": 91,
      "accurracy": 100
    },
    {
      "planetIndex": 169,
      "missionsWon": 20989517,
      "missionsLost": 2480460,
      "missionTime": 45566143504,
      "bugKills": 6012691462,
      "automatonKills": 750,
      "illuminateKills": 0,
      "bulletsFired": 31165204784,
      "bulletsHit": 37202389400,
      "timePlayed": 45566143504,
      "deaths": 111244343,
      "revives": 0,
      "friendlies": 20445547,
      "missionSuccessRate": 89,
      "accurracy": 100
    },
    {
      "planetIndex": 170,
      "missionsWon": 15102564,
      "missionsLost": 1639890,
      "missionTime": 35661471154,
      "bugKills": 4472635437,
      "automatonKills": 214,
      "illuminateKills": 0,
      "bulletsFired": 24092390717,
      "bulletsHit": 28705973300,
      "timePlayed": 35661471154,
      "deaths": 86637552,
      "revives": 0,
      "friendlies": 14980371,
      "missionSuccessRate": 90,
      "accurracy": 100
    },
    {
      "planetIndex": 194,
      "missionsWon": 7534036,
      "missionsLost": 792143,
      "missionTime": 28976951783,
      "bugKills": 188,
      "automatonKills": 2071836109,
      "illuminateKills": 0,
      "bulletsFired": 12722452908,
      "bulletsHit": 13229839424,
      "timePlayed": 28976951783,
      "deaths": 67771409,
      "revives": 0,
      "friendlies": 6654449,
      "missionSuccessRate": 90,
      "accurracy": 100
    },
    {
      "planetIndex": 195,
      "missionsWon": 3311227,
      "missionsLost": 270817,
      "missionTime": 12234265273,
      "bugKills": 2,
      "automatonKills": 839046563,
      "illuminateKills": 0,
      "bulletsFired": 6204110004,
      "bulletsHit": 6363168354,
      "timePlayed": 12234265273,
      "deaths": 29892019,
      "revives": 0,
      "friendlies": 2619682,
      "missionSuccessRate": 92,
      "accurracy": 100
    },
    {
      "planetIndex": 196,
      "missionsWon": 5120258,
      "missionsLost": 714072,
      "missionTime": 5329119990,
      "bugKills": 597,
      "automatonKills": 376331359,
      "illuminateKills": 0,
      "bulletsFired": 2769826362,
      "bulletsHit": 2757442690,
      "timePlayed": 5329119990,
      "deaths": 25032439,
      "revives": 0,
      "friendlies": 2364505,
      "missionSuccessRate": 87,
      "accurracy": 99
    },
    {
      "planetIndex": 197,
      "missionsWon": 3863901,
      "missionsLost": 387942,
      "missionTime": 2983494533,
      "bugKills": 24729,
      "automatonKills": 231287224,
      "illuminateKills": 0,
      "bulletsFired": 1614486367,
      "bulletsHit": 1216739150,
      "timePlayed": 2983494533,
      "deaths": 12078117,
      "revives": 0,
      "friendlies": 1473398,
      "missionSuccessRate": 90,
      "accurracy": 75
    },
    {
      "planetIndex": 198,
      "missionsWon": 4732577,
      "missionsLost": 456616,
      "missionTime": 17455335890,
      "bugKills": 0,
      "automatonKills": 1180158863,
      "illuminateKills": 0,
      "bulletsFired": 7322858312,
      "bulletsHit": 7679770764,
      "timePlayed": 17455335890,
      "deaths": 41489570,
      "revives": 0,
      "friendlies": 4251964,
      "missionSuccessRate": 91,
      "accurracy": 100
    },
    {
      "planetIndex": 199,
      "missionsWon": 3202066,
      "missionsLost": 372603,
      "missionTime": 12040852951,
      "bugKills": 444,
      "automatonKills": 828937803,
      "illuminateKills": 0,
      "bulletsFired": 5364179389,
      "bulletsHit": 5424741784,
      "timePlayed": 12040852951,
      "deaths": 32388465,
      "revives": 0,
      "friendlies": 2856552,
      "missionSuccessRate": 89,
      "accurracy": 100
    },
    {
      "planetIndex": 200,
      "missionsWon": 1060795,
      "missionsLost": 169259,
      "missionTime": 3917665173,
      "bugKills": 43,
      "automatonKills": 277518170,
      "illuminateKills": 0,
      "bulletsFired": 1811047635,
      "bulletsHit": 1863862146,
      "timePlayed": 3917665173,
      "deaths": 10484423,
      "revives": 0,
      "friendlies": 1092874,
      "missionSuccessRate": 86,
      "accurracy": 100
    },
    {
      "planetIndex": 201,
      "missionsWon": 936492,
      "missionsLost": 147299,
      "missionTime": 3360834978,
      "bugKills": 97,
      "automatonKills": 221151747,
      "illuminateKills": 0,
      "bulletsFired": 1468003203,
      "bulletsHit": 1482878072,
      "timePlayed": 3360834978,
      "deaths": 9797906,
      "revives": 0,
      "friendlies": 995186,
      "missionSuccessRate": 86,
      "accurracy": 100
    },
    {
      "planetIndex": 202,
      "missionsWon": 50,
      "missionsLost": 6,
      "missionTime": 143975,
      "bugKills": 0,
      "automatonKills": 10482,
      "illuminateKills": 0,
      "bulletsFired": 76320,
      "bulletsHit": 80386,
      "timePlayed": 143975,
      "deaths": 396,
      "revives": 0,
      "friendlies": 20,
      "missionSuccessRate": 89,
      "accurracy": 100
    },
    {
      "planetIndex": 203,
      "missionsWon": 8810269,
      "missionsLost": 1310180,
      "missionTime": 30490610976,
      "bugKills": 1315,
      "automatonKills": 2033042354,
      "illuminateKills": 0,
      "bulletsFired": 13428384157,
      "bulletsHit": 13754118266,
      "timePlayed": 30490610976,
      "deaths": 87013424,
      "revives": 0,
      "friendlies": 7818493,
      "missionSuccessRate": 87,
      "accurracy": 100
    },
    {
      "planetIndex": 204,
      "missionsWon": 117373,
      "missionsLost": 12212,
      "missionTime": 321702801,
      "bugKills": 45,
      "automatonKills": 21181449,
      "illuminateKills": 0,
      "bulletsFired": 135654031,
      "bulletsHit": 135750632,
      "timePlayed": 321702801,
      "deaths": 928274,
      "revives": 0,
      "friendlies": 87228,
      "missionSuccessRate": 90,
      "accurracy": 100
    },
    {
      "planetIndex": 211,
      "missionsWon": 3542800,
      "missionsLost": 348915,
      "missionTime": 5725394880,
      "bugKills": 662453957,
      "automatonKills": 485,
      "illuminateKills": 0,
      "bulletsFired": 3676012503,
      "bulletsHit": 4384776128,
      "timePlayed": 5725394880,
      "deaths": 16864473,
      "revives": 0,
      "friendlies": 2627662,
      "missionSuccessRate": 91,
      "accurracy": 100
    },
    {
      "planetIndex": 212,
      "missionsWon": 14990814,
      "missionsLost": 1724386,
      "missionTime": 32320023544,
      "bugKills": 4160236866,
      "automatonKills": 307,
      "illuminateKills": 0,
      "bulletsFired": 21485641051,
      "bulletsHit": 25682902150,
      "timePlayed": 32320023544,
      "deaths": 84209135,
      "revives": 0,
      "friendlies": 14349340,
      "missionSuccessRate": 89,
      "accurracy": 100
    },
    {
      "planetIndex": 214,
      "missionsWon": 3436375,
      "missionsLost": 215760,
      "missionTime": 11534428784,
      "bugKills": 1433235453,
      "automatonKills": 0,
      "illuminateKills": 0,
      "bulletsFired": 6482060418,
      "bulletsHit": 7926591614,
      "timePlayed": 11534428784,
      "deaths": 26517933,
      "revives": 0,
      "friendlies": 4409159,
      "missionSuccessRate": 94,
      "accurracy": 100
    },
    {
      "planetIndex": 217,
      "missionsWon": 1536616,
      "missionsLost": 137115,
      "missionTime": 5345785306,
      "bugKills": 671340251,
      "automatonKills": 0,
      "illuminateKills": 0,
      "bulletsFired": 3048932599,
      "bulletsHit": 3739305488,
      "timePlayed": 5345785306,
      "deaths": 12331076,
      "revives": 0,
      "friendlies": 2055621,
      "missionSuccessRate": 91,
      "accurracy": 100
    },
    {
      "planetIndex": 238,
      "missionsWon": 5661365,
      "missionsLost": 482029,
      "missionTime": 16198243148,
      "bugKills": 20049,
      "automatonKills": 1034134765,
      "illuminateKills": 0,
      "bulletsFired": 7920137037,
      "bulletsHit": 7584222716,
      "timePlayed": 16198243148,
      "deaths": 43811852,
      "revives": 0,
      "friendlies": 3998620,
      "missionSuccessRate": 92,
      "accurracy": 95
    },
    {
      "planetIndex": 239,
      "missionsWon": 4868,
      "missionsLost": 1866,
      "missionTime": 4580428,
      "bugKills": 0,
      "automatonKills": 327891,
      "illuminateKills": 0,
      "bulletsFired": 2557396,
      "bulletsHit": 2517218,
      "timePlayed": 4580428,
      "deaths": 23802,
      "revives": 0,
      "friendlies": 1150,
      "missionSuccessRate": 72,
      "accurracy": 98
    },
    {
      "planetIndex": 240,
      "missionsWon": 5329163,
      "missionsLost": 663597,
      "missionTime": 3880026603,
      "bugKills": 5338,
      "automatonKills": 307781825,
      "illuminateKills": 0,
      "bulletsFired": 2080485129,
      "bulletsHit": 1596811429,
      "timePlayed": 3880026603,
      "deaths": 16038115,
      "revives": 0,
      "friendlies": 1925877,
      "missionSuccessRate": 88,
      "accurracy": 76
    },
    {
      "planetIndex": 241,
      "missionsWon": 7536628,
      "missionsLost": 985750,
      "missionTime": 8431524343,
      "bugKills": 37206,
      "automatonKills": 664964277,
      "illuminateKills": 0,
      "bulletsFired": 4653289315,
      "bulletsHit": 4321196439,
      "timePlayed": 8431524343,
      "deaths": 31830993,
      "revives": 0,
      "friendlies": 3164397,
      "missionSuccessRate": 88,
      "accurracy": 92
    },
    {
      "planetIndex": 242,
      "missionsWon": 3318794,
      "missionsLost": 469504,
      "missionTime": 3452119840,
      "bugKills": 1510,
      "automatonKills": 254601564,
      "illuminateKills": 0,
      "bulletsFired": 1786307628,
      "bulletsHit": 1778481340,
      "timePlayed": 3452119840,
      "deaths": 15902500,
      "revives": 0,
      "friendlies": 1499328,
      "missionSuccessRate": 87,
      "accurracy": 99
    },
    {
      "planetIndex": 243,
      "missionsWon": 2774844,
      "missionsLost": 306179,
      "missionTime": 4714530971,
      "bugKills": 245,
      "automatonKills": 341023369,
      "illuminateKills": 0,
      "bulletsFired": 2664007465,
      "bulletsHit": 2790001000,
      "timePlayed": 4714530971,
      "deaths": 15199176,
      "revives": 0,
      "friendlies": 1469001,
      "missionSuccessRate": 90,
      "accurracy": 100
    },
    {
      "planetIndex": 244,
      "missionsWon": 593841,
      "missionsLost": 89228,
      "missionTime": 2399407245,
      "bugKills": 0,
      "automatonKills": 175607031,
      "illuminateKills": 0,
      "bulletsFired": 1148353834,
      "bulletsHit": 1186075310,
      "timePlayed": 2399407245,
      "deaths": 6065856,
      "revives": 0,
      "friendlies": 623708,
      "missionSuccessRate": 86,
      "accurracy": 100
    },
    {
      "planetIndex": 245,
      "missionsWon": 142797,
      "missionsLost": 30650,
      "missionTime": 548842295,
      "bugKills": 0,
      "automatonKills": 38938861,
      "illuminateKills": 0,
      "bulletsFired": 242926733,
      "bulletsHit": 249061844,
      "timePlayed": 548842295,
      "deaths": 1572044,
      "revives": 0,
      "friendlies": 172063,
      "missionSuccessRate": 82,
      "accurracy": 100
    },
    {
      "planetIndex": 247,
      "missionsWon": 5435,
      "missionsLost": 2164,
      "missionTime": 24264488,
      "bugKills": 0,
      "automatonKills": 1910310,
      "illuminateKills": 0,
      "bulletsFired": 9738310,
      "bulletsHit": 10389590,
      "timePlayed": 24264488,
      "deaths": 67792,
      "revives": 0,
      "friendlies": 9543,
      "missionSuccessRate": 71,
      "accurracy": 100
    },
    {
      "planetIndex": 248,
      "missionsWon": 54,
      "missionsLost": 8,
      "missionTime": 169996,
      "bugKills": 0,
      "automatonKills": 10782,
      "illuminateKills": 0,
      "bulletsFired": 81925,
      "bulletsHit": 82338,
      "timePlayed": 169996,
      "deaths": 534,
      "revives": 0,
      "friendlies": 46,
      "missionSuccessRate": 87,
      "accurracy": 100
    },
    {
      "planetIndex": 259,
      "missionsWon": 3690616,
      "missionsLost": 269344,
      "missionTime": 11728809373,
      "bugKills": 1503431326,
      "automatonKills": 0,
      "illuminateKills": 0,
      "bulletsFired": 7242382334,
      "bulletsHit": 8664604898,
      "timePlayed": 11728809373,
      "deaths": 26029244,
      "revives": 0,
      "friendlies": 4420144,
      "missionSuccessRate": 93,
      "accurracy": 100
    },
    {
      "planetIndex": 260,
      "missionsWon": 3033,
      "missionsLost": 0,
      "missionTime": 1045,
      "bugKills": 0,
      "automatonKills": 8,
      "illuminateKills": 12,
      "bulletsFired": 508,
      "bulletsHit": 262,
      "timePlayed": 1045,
      "deaths": 4,
      "revives": 0,
      "friendlies": 0,
      "missionSuccessRate": 100,
      "accurracy": 51
    },
    {
      "planetIndex": 261,
      "missionsWon": 1,
      "missionsLost": 0,
      "missionTime": 0,
      "bugKills": 0,
      "automatonKills": 0,
      "illuminateKills": 0,
      "bulletsFired": 0,
      "bulletsHit": 0,
      "timePlayed": 0,
      "deaths": 0,
      "revives": 0,
      "friendlies": 0,
      "missionSuccessRate": 100,
      "accurracy": 0
    }
  ]
}